Workbook

Sheet Removed 15
A1: seed | B1: cycle | C1: investor_percent_earning_share | D1: investor_count | E1: investment_rotation_years | F1: nursery_count | G1: police_count | H1: member_count | I1: exotic_price_per_bdft | J1: native_price_per_bdft | K1: Seedling | L1: Sapling | M1: Pole | N1: Adult | O1: Native | P1: Seedling | Q1: Sapling | R1: Pole | S1: Adult | T1: Exotic | U1: Total | V1: management_running_cost | W1: ITP_running_earning | X1: net_running_earning | Y1: m_partners_earning | Z1: average m_partners_earning | AA1: m_independent_earning | AB1: average m_independent_earning | AC1: own_laborer | AD1: member_laborer | AE1: independent_laborer | AF1: investor_total_profit | AG1: total_investment_cost | AH1: total net investor profit | AI1: average net investor profit | AJ1: total_investments | AK1: inv_harvested_trees | AL1: with_investment | AM1: Profitable?
A2: 10 | B2: 193 | C2: 0.3 | D2: 5 | E2: 15 | F2: 3 | G2: 3 | H2: 30 | I2: 45.06 | J2: 49.35 | K2: 56130 | L2: 96236 | M2: 28211 | N2: 9944 | O2: =SUM(K2:N2) -> 190521 | P2: 29180 | Q2: 32631 | R2: 3480 | S2: 31158 | T2: =SUM(P2:S2) -> 96449 | U2: =O2+T2 -> 286970 | V2: 10795377 | W2: 4787166.8 | X2: -6008210.7 | Y2: 10515649 | Z2: =Y2/AD2 -> 6078.4098 | AA2: 1.4950462e+08 | AB2: =AA2/AE2 -> 94683.102 | AC2: 724 | AD2: 1730 | AE2: 1579 | AF2: 942069.87 | AG2: 836279.55 | AH2: =AF2-AG2 -> 105790.32 | AI2: =AH2/D2 -> 21158.065 | AJ2: 5 | AK2: 0 | AL2: TRUE | AM2: =IF('MANOVA '!M44, 1, 0) -> 0
A3: 10 | B3: 188 | C3: 0.3 | D3: 5 | E3: 15 | F3: 3 | G3: 3 | H3: 30 | I3: 90.12 | J3: 98.7 | K3: 76141 | L3: 84920 | M3: 28577 | N3: 9580 | O3: =SUM(K3:N3) -> 199218 | P3: 4767 | Q3: 35386 | R3: 3891 | S3: 28179 | T3: =SUM(P3:S3) -> 72223 | U3: =O3+T3 -> 271441 | V3: 10797015 | W3: 8570550.9 | X3: -2226463.7 | Y3: 12649332 | Z3: =Y3/AD3 -> 7736.5944 | AA3: 4.7381087e+08 | AB3: =AA3/AE3 -> 248458.77 | AC3: 583 | AD3: 1635 | AE3: 1907 | AF3: 1782884.6 | AG3: 836279.55 | AH3: =AF3-AG3 -> 946605.07 | AI3: =AH3/D3 -> 189321.01 | AJ3: 5 | AK3: 0 | AL3: TRUE | AM3: =IF('MANOVA '!M45, 1, 0) -> 0
A4: 10 | B4: 193 | C4: 0.3 | D4: 5 | E4: 15 | F4: 3 | G4: 3 | H4: 15 | I4: 45.06 | J4: 49.35 | K4: 60779 | L4: 96973 | M4: 26668 | N4: 10965 | O4: =SUM(K4:N4) -> 195385 | P4: 32250 | Q4: 35659 | R4: 3391 | S4: 34557 | T4: =SUM(P4:S4) -> 105857 | U4: =O4+T4 -> 301242 | V4: 8062891.9 | W4: 4548429.5 | X4: -3514462.4 | Y4: 5096634.5 | Z4: =Y4/AD4 -> 4113.5065 | AA4: 68232273 | AB4: =AA4/AE4 -> 98034.875 | AC4: 344 | AD4: 1239 | AE4: 696 | AF4: 734402.24 | AG4: 836279.55 | AH4: =AF4-AG4 -> -101877.31 | AI4: =AH4/D4 -> -20375.462 | AJ4: 5 | AK4: 0 | AL4: TRUE | AM4: =IF('MANOVA '!M46, 1, 0) -> 0
A5: 10 | B5: 188 | C5: 0.3 | D5: 5 | E5: 15 | F5: 3 | G5: 3 | H5: 15 | I5: 90.12 | J5: 98.7 | K5: 83744 | L5: 84954 | M5: 27765 | N5: 11246 | O5: =SUM(K5:N5) -> 207709 | P5: 5219 | Q5: 42636 | R5: 4010 | S5: 36044 | T5: =SUM(P5:S5) -> 87909 | U5: =O5+T5 -> 295618 | V5: 10589209 | W5: 9271102.6 | X5: -1318106.5 | Y5: 6858424.8 | Z5: =Y5/AD5 -> 4017.8236 | AA5: 67646764 | AB5: =AA5/AE5 -> 336551.06 | AC5: 174 | AD5: 1707 | AE5: 201 | AF5: 3157034.7 | AG5: 836279.55 | AH5: =AF5-AG5 -> 2320755.1 | AI5: =AH5/D5 -> 464151.03 | AJ5: 5 | AK5: 10 | AL5: TRUE | AM5: =IF('MANOVA '!M47, 1, 0) -> 0
A6: 10 | B6: 193 | C6: 0.3 | D6: 5 | E6: 15 | F6: 3 | G6: 1 | H6: 30 | I6: 45.06 | J6: 49.35 | K6: 55624 | L6: 93590 | M6: 29025 | N6: 9634 | O6: =SUM(K6:N6) -> 187873 | P6: 27538 | Q6: 32831 | R6: 3271 | S6: 29536 | T6: =SUM(P6:S6) -> 93176 | U6: =O6+T6 -> 281049 | V6: 10124349 | W6: 5164071 | X6: -4960278.4 | Y6: 7813527.1 | Z6: =Y6/AD6 -> 4295.5069 | AA6: 1.9752276e+08 | AB6: =AA6/AE6 -> 101501.93 | AC6: 586 | AD6: 1819 | AE6: 1946 | AF6: 1262239.1 | AG6: 836279.55 | AH6: =AF6-AG6 -> 425959.6 | AI6: =AH6/D6 -> 85191.92 | AJ6: 5 | AK6: 0 | AL6: TRUE | AM6: =IF('MANOVA '!M48, 1, 0) -> 0
A7: 10 | B7: 188 | C7: 0.3 | D7: 5 | E7: 15 | F7: 3 | G7: 1 | H7: 30 | I7: 90.12 | J7: 98.7 | K7: 75087 | L7: 85301 | M7: 28287 | N7: 9416 | O7: =SUM(K7:N7) -> 198091 | P7: 4646 | Q7: 36258 | R7: 3905 | S7: 27656 | T7: =SUM(P7:S7) -> 72465 | U7: =O7+T7 -> 270556 | V7: 8181738.9 | W7: 6966386.6 | X7: -1215352.3 | Y7: 8982625 | Z7: =Y7/AD7 -> 6738.6534 | AA7: 5.0595782e+08 | AB7: =AA7/AE7 -> 244070.34 | AC7: 588 | AD7: 1333 | AE7: 2073 | AF7: 401815.26 | AG7: 836279.55 | AH7: =AF7-AG7 -> -434464.29 | AI7: =AH7/D7 -> -86892.859 | AJ7: 5 | AK7: 46 | AL7: TRUE | AM7: =IF('MANOVA '!M49, 1, 0) -> 0
A8: 10 | B8: 192 | C8: 0.3 | D8: 5 | E8: 15 | F8: 3 | G8: 1 | H8: 15 | I8: 45.06 | J8: 49.35 | K8: 65860 | L8: 96265 | M8: 27488 | N8: 11502 | O8: =SUM(K8:N8) -> 201115 | P8: 4753 | Q8: 39124 | R8: 3563 | S8: 37591 | T8: =SUM(P8:S8) -> 85031 | U8: =O8+T8 -> 286146 | V8: 11197638 | W8: 5223145.9 | X8: -5974492.4 | Y8: 8056747.9 | Z8: =Y8/AD8 -> 3984.544 | AA8: 0 | AB8: 0 | AC8: 144 | AD8: 2022 | AE8: 0 | AF8: 1188262.3 | AG8: 836279.55 | AH8: =AF8-AG8 -> 351982.76 | AI8: =AH8/D8 -> 70396.553 | AJ8: 5 | AK8: 1 | AL8: TRUE | AM8: =IF('MANOVA '!M50, 1, 0) -> 0
A9: 10 | B9: 188 | C9: 0.3 | D9: 5 | E9: 15 | F9: 3 | G9: 1 | H9: 15 | I9: 90.12 | J9: 98.7 | K9: 83862 | L9: 85144 | M9: 27628 | N9: 11355 | O9: =SUM(K9:N9) -> 207989 | P9: 5337 | Q9: 43492 | R9: 4001 | S9: 37104 | T9: =SUM(P9:S9) -> 89934 | U9: =O9+T9 -> 297923 | V9: 11119606 | W9: 9574713.2 | X9: -1544892.7 | Y9: 7875108.6 | Z9: =Y9/AD9 -> 3981.3492 | AA9: 0 | AB9: 0 | AC9: 136 | AD9: 1978 | AE9: 0 | AF9: 3430220.4 | AG9: 836279.55 | AH9: =AF9-AG9 -> 2593940.8 | AI9: =AH9/D9 -> 518788.17 | AJ9: 5 | AK9: 13 | AL9: TRUE | AM9: =IF('MANOVA '!M51, 1, 0) -> 0
A10: 10 | B10: 193 | C10: 0.3 | D10: 5 | E10: 15 | F10: 1 | G10: 3 | H10: 30 | I10: 45.06 | J10: 49.35 | K10: 54206 | L10: 92569 | M10: 27471 | N10: 9304 | O10: =SUM(K10:N10) -> 183550 | P10: 25735 | Q10: 30154 | R10: 3302 | S10: 27773 | T10: =SUM(P10:S10) -> 86964 | U10: =O10+T10 -> 270514 | V10: 8887766.5 | W10: 4411704.1 | X10: -4476062.4 | Y10: 6517385 | Z10: =Y10/AD10 -> 5013.3731 | AA10: 2.2657946e+08 | AB10: =AA10/AE10 -> 99639.163 | AC10: 617 | AD10: 1300 | AE10: 2274 | AF10: 1057647.9 | AG10: 836279.55 | AH10: =AF10-AG10 -> 221368.32 | AI10: =AH10/D10 -> 44273.663 | AJ10: 5 | AK10: 0 | AL10: TRUE | AM10: =IF('MANOVA '!M52, 1, 0) -> 0
A11: 10 | B11: 188 | C11: 0.3 | D11: 5 | E11: 15 | F11: 1 | G11: 3 | H11: 30 | I11: 90.12 | J11: 98.7 | K11: 73479 | L11: 80058 | M11: 29606 | N11: 9365 | O11: =SUM(K11:N11) -> 192508 | P11: 4579 | Q11: 35130 | R11: 3834 | S11: 27574 | T11: =SUM(P11:S11) -> 71117 | U11: =O11+T11 -> 263625 | V11: 9596064.7 | W11: 7414965.4 | X11: -2181099.3 | Y11: 11009126 | Z11: =Y11/AD11 -> 7388.6751 | AA11: 4.7832283e+08 | AB11: =AA11/AE11 -> 227123.85 | AC11: 630 | AD11: 1490 | AE11: 2106 | AF11: 1667189.1 | AG11: 836279.55 | AH11: =AF11-AG11 -> 830909.51 | AI11: =AH11/D11 -> 166181.9 | AJ11: 5 | AK11: 0 | AL11: TRUE | AM11: =IF('MANOVA '!M53, 1, 0) -> 0
A12: 10 | B12: 193 | C12: 0.3 | D12: 5 | E12: 15 | F12: 1 | G12: 3 | H12: 15 | I12: 45.06 | J12: 49.35 | K12: 59890 | L12: 94866 | M12: 28047 | N12: 10761 | O12: =SUM(K12:N12) -> 193564 | P12: 31385 | Q12: 34663 | R12: 3385 | S12: 33515 | T12: =SUM(P12:S12) -> 102948 | U12: =O12+T12 -> 296512 | V12: 8173867.4 | W12: 4512427 | X12: -3661440.4 | Y12: 5295664.5 | Z12: =Y12/AD12 -> 4867.3387 | AA12: 1.067828e+08 | AB12: =AA12/AE12 -> 123877.95 | AC12: 481 | AD12: 1088 | AE12: 862 | AF12: 1142154.3 | AG12: 836279.55 | AH12: =AF12-AG12 -> 305874.73 | AI12: =AH12/D12 -> 61174.945 | AJ12: 5 | AK12: 0 | AL12: TRUE | AM12: =IF('MANOVA '!M54, 1, 0) -> 0
A13: 10 | B13: 188 | C13: 0.3 | D13: 5 | E13: 15 | F13: 1 | G13: 3 | H13: 15 | I13: 90.12 | J13: 98.7 | K13: 82329 | L13: 83864 | M13: 27897 | N13: 10985 | O13: =SUM(K13:N13) -> 205075 | P13: 5221 | Q13: 40936 | R13: 4013 | S13: 34490 | T13: =SUM(P13:S13) -> 84660 | U13: =O13+T13 -> 289735 | V13: 9143625.7 | W13: 7991009.7 | X13: -1152616 | Y13: 6841452.8 | Z13: =Y13/AD13 -> 5037.8887 | AA13: 1.4556912e+08 | AB13: =AA13/AE13 -> 298297.37 | AC13: 252 | AD13: 1358 | AE13: 488 | AF13: 2937034.9 | AG13: 836279.55 | AH13: =AF13-AG13 -> 2100755.4 | AI13: =AH13/D13 -> 420151.08 | AJ13: 5 | AK13: 10 | AL13: TRUE | AM13: =IF('MANOVA '!M55, 1, 0) -> 0
A14: 10 | B14: 193 | C14: 0.3 | D14: 5 | E14: 15 | F14: 1 | G14: 1 | H14: 30 | I14: 45.06 | J14: 49.35 | K14: 53401 | L14: 90211 | M14: 27370 | N14: 9201 | O14: =SUM(K14:N14) -> 180183 | P14: 24949 | Q14: 29523 | R14: 3381 | S14: 27027 | T14: =SUM(P14:S14) -> 84880 | U14: =O14+T14 -> 265063 | V14: 8752974 | W14: 3990569.4 | X14: -4762404.5 | Y14: 7131392.7 | Z14: =Y14/AD14 -> 5382.1832 | AA14: 2.5298646e+08 | AB14: =AA14/AE14 -> 104886.59 | AC14: 425 | AD14: 1325 | AE14: 2412 | AF14: 694847.83 | AG14: 836279.55 | AH14: =AF14-AG14 -> -141431.72 | AI14: =AH14/D14 -> -28286.344 | AJ14: 5 | AK14: 0 | AL14: TRUE | AM14: =IF('MANOVA '!M56, 1, 0) -> 0
A15: 10 | B15: 188 | C15: 0.3 | D15: 5 | E15: 15 | F15: 1 | G15: 1 | H15: 30 | I15: 90.12 | J15: 98.7 | K15: 76269 | L15: 82452 | M15: 29989 | N15: 9889 | O15: =SUM(K15:N15) -> 198599 | P15: 4921 | Q15: 37049 | R15: 3844 | S15: 30374 | T15: =SUM(P15:S15) -> 76188 | U15: =O15+T15 -> 274787 | V15: 9690919.1 | W15: 7735615.7 | X15: -1955303.4 | Y15: 16383262 | Z15: =Y15/AD15 -> 10604.053 | AA15: 3.5629874e+08 | AB15: =AA15/AE15 -> 217919.72 | AC15: 646 | AD15: 1545 | AE15: 1635 | AF15: 1938377.3 | AG15: 836279.55 | AH15: =AF15-AG15 -> 1102097.7 | AI15: =AH15/D15 -> 220419.54 | AJ15: 5 | AK15: 0 | AL15: TRUE | AM15: =IF('MANOVA '!M57, 1, 0) -> 0
A16: 10 | B16: 193 | C16: 0.3 | D16: 5 | E16: 15 | F16: 1 | G16: 1 | H16: 15 | I16: 45.06 | J16: 49.35 | K16: 61037 | L16: 95544 | M16: 27732 | N16: 10778 | O16: =SUM(K16:N16) -> 195091 | P16: 31298 | Q16: 35952 | R16: 3456 | S16: 33670 | T16: =SUM(P16:S16) -> 104376 | U16: =O16+T16 -> 299467 | V16: 7572285.4 | W16: 4680010.2 | X16: -2892275.2 | Y16: 5501423.6 | Z16: =Y16/AD16 -> 5269.5629 | AA16: 1.0373256e+08 | AB16: =AA16/AE16 -> 129503.83 | AC16: 308 | AD16: 1044 | AE16: 801 | AF16: 1285793.9 | AG16: 836279.55 | AH16: =AF16-AG16 -> 449514.35 | AI16: =AH16/D16 -> 89902.869 | AJ16: 5 | AK16: 0 | AL16: TRUE | AM16: =IF('MANOVA '!M58, 1, 0) -> 0
A17: 10 | B17: 188 | C17: 0.3 | D17: 5 | E17: 15 | F17: 1 | G17: 1 | H17: 15 | I17: 90.12 | J17: 98.7 | K17: 80557 | L17: 82953 | M17: 28137 | N17: 10764 | O17: =SUM(K17:N17) -> 202411 | P17: 5166 | Q17: 40266 | R17: 4024 | S17: 33884 | T17: =SUM(P17:S17) -> 83340 | U17: =O17+T17 -> 285751 | V17: 9158247.2 | W17: 8113860.1 | X17: -1044387 | Y17: 5961331.6 | Z17: =Y17/AD17 -> 4571.5733 | AA17: 1.6503634e+08 | AB17: =AA17/AE17 -> 261133.45 | AC17: 335 | AD17: 1304 | AE17: 632 | AF17: 3042328.9 | AG17: 836279.55 | AH17: =AF17-AG17 -> 2206049.4 | AI17: =AH17/D17 -> 441209.88 | AJ17: 5 | AK17: 10 | AL17: TRUE | AM17: =IF('MANOVA '!M59, 1, 0) -> 0
A18: 10 | B18: 128 | C18: 0.3 | D18: 5 | E18: 10 | F18: 3 | G18: 3 | H18: 30 | I18: 45.06 | J18: 49.35 | K18: 68759 | L18: 56477 | M18: 33213 | N18: 8967 | O18: =SUM(K18:N18) -> 167416 | P18: 19025 | Q18: 26741 | R18: 7991 | S18: 30092 | T18: =SUM(P18:S18) -> 83849 | U18: =O18+T18 -> 251265 | V18: 7550984.7 | W18: 3683648.6 | X18: -3867336.1 | Y18: 5337408 | Z18: =Y18/AD18 -> 4744.3627 | AA18: 1.2264861e+08 | AB18: =AA18/AE18 -> 93198.035 | AC18: 446 | AD18: 1125 | AE18: 1316 | AF18: 355893.42 | AG18: 569564.8 | AH18: =AF18-AG18 -> -213671.38 | AI18: =AH18/D18 -> -42734.277 | AJ18: 5 | AK18: 0 | AL18: TRUE | AM18: =IF('MANOVA '!M60, 1, 0) -> 0
A19: 10 | B19: 128 | C19: 0.3 | D19: 5 | E19: 10 | F19: 3 | G19: 3 | H19: 30 | I19: 90.12 | J19: 98.7 | K19: 68786 | L19: 56490 | M19: 33230 | N19: 8976 | O19: =SUM(K19:N19) -> 167482 | P19: 19027 | Q19: 26737 | R19: 7988 | S19: 30063 | T19: =SUM(P19:S19) -> 83815 | U19: =O19+T19 -> 251297 | V19: 7535004.1 | W19: 6797732.5 | X19: -737271.61 | Y19: 6378573 | Z19: =Y19/AD19 -> 5669.8426 | AA19: 2.4721679e+08 | AB19: =AA19/AE19 -> 187854.7 | AC19: 446 | AD19: 1125 | AE19: 1316 | AF19: 711786.83 | AG19: 569564.8 | AH19: =AF19-AG19 -> 142222.03 | AI19: =AH19/D19 -> 28444.406 | AJ19: 5 | AK19: 0 | AL19: TRUE | AM19: =IF('MANOVA '!M61, 1, 0) -> 0
A20: 10 | B20: 128 | C20: 0.3 | D20: 5 | E20: 10 | F20: 3 | G20: 3 | H20: 15 | I20: 45.06 | J20: 49.35 | K20: 74846 | L20: 54690 | M20: 34145 | N20: 10125 | O20: =SUM(K20:N20) -> 173806 | P20: 22068 | Q20: 29257 | R20: 8264 | S20: 34335 | T20: =SUM(P20:S20) -> 93924 | U20: =O20+T20 -> 267730 | V20: 7664517.5 | W20: 3971933.5 | X20: -3692584 | Y20: 4384756.8 | Z20: =Y20/AD20 -> 4011.6714 | AA20: 31151020 | AB20: =AA20/AE20 -> 154212.97 | AC20: 181 | AD20: 1093 | AE20: 202 | AF20: 941926.36 | AG20: 569564.8 | AH20: =AF20-AG20 -> 372361.56 | AI20: =AH20/D20 -> 74472.312 | AJ20: 5 | AK20: 9 | AL20: TRUE | AM20: =IF('MANOVA '!M62, 1, 0) -> 0
A21: 10 | B21: 128 | C21: 0.3 | D21: 5 | E21: 10 | F21: 3 | G21: 3 | H21: 15 | I21: 90.12 | J21: 98.7 | K21: 74846 | L21: 54690 | M21: 34145 | N21: 10125 | O21: =SUM(K21:N21) -> 173806 | P21: 22068 | Q21: 29257 | R21: 8264 | S21: 34335 | T21: =SUM(P21:S21) -> 93924 | U21: =O21+T21 -> 267730 | V21: 7664517.5 | W21: 7374302.2 | X21: -290215.34 | Y21: 4397409.2 | Z21: =Y21/AD21 -> 4023.2472 | AA21: 62302039 | AB21: =AA21/AE21 -> 308425.94 | AC21: 181 | AD21: 1093 | AE21: 202 | AF21: 1883852.7 | AG21: 569564.8 | AH21: =AF21-AG21 -> 1314287.9 | AI21: =AH21/D21 -> 262857.58 | AJ21: 5 | AK21: 9 | AL21: TRUE | AM21: =IF('MANOVA '!M63, 1, 0) -> 0
... A33: 10 | B33: 128 | C33: 0.3 | D33: 5 | E33: 10 | F33: 1 | G33: 1 | H33: 15 | I33: 90.12 | J33: 98.7 | K33: 73979 | L33: 55194 | M33: 34104 | N33: 9911 | O33: =SUM(K33:N33) -> 173188 | P33: 21552 | Q33: 28608 | R33: 8443 | S33: 33572 | T33: =SUM(P33:S33) -> 92175 | U33: =O33+T33 -> 265363 | V33: 6476582.2 | W33: 6110820.1 | X33: -365762.16 | Y33: 4378735.7 | Z33: =Y33/AD33 -> 4975.836 | AA33: 92326472 | AB33: =AA33/AE33 -> 265305.95 | AC33: 228 | AD33: 880 | AE33: 348 | AF33: 1683143.8 | AG33: 569564.8 | AH33: =AF33-AG33 -> 1113579 | AI33: =AH33/D33 -> 222715.79 | AJ33: 5 | AK33: 9 | AL33: TRUE | AM33: =IF('MANOVA '!M75, 1, 0) -> 0
A34: 10 | B34: 199 | C34: 0.3 | D34: 30 | E34: 15 | F34: 3 | G34: 3 | H34: 30 | I34: 45.06 | J34: 49.35 | K34: 89229 | L34: 96079 | M34: 27487 | N34: 12175 | O34: =SUM(K34:N34) -> 224970 | P34: 25561 | Q34: 39899 | R34: 3162 | S34: 38011 | T34: =SUM(P34:S34) -> 106633 | U34: =O34+T34 -> 331603 | V34: 39766899 | W34: 15244202 | X34: -24522697 | Y34: 19442898 | Z34: =Y34/AD34 -> 3898.7162 | AA34: 0 | AB34: 0 | AC34: 3175 | AD34: 4987 | AE34: 0 | AF34: 2633599 | AG34: 5017677.3 | AH34: =AF34-AG34 -> -2384078.3 | AI34: =AH34/D34 -> -79469.278 | AJ34: 30 | AK34: 492 | AL34: TRUE | AM34: =IF('MANOVA '!M76, 1, 0) -> 0
A35: 10 | B35: 198 | C35: 0.3 | D35: 30 | E35: 15 | F35: 3 | G35: 3 | H35: 30 | I35: 90.12 | J35: 98.7 | K35: 80000 | L35: 96000 | M35: 27065 | N35: 12115 | O35: =SUM(K35:N35) -> 215180 | P35: 26543 | Q35: 41092 | R35: 3271 | S35: 38350 | T35: =SUM(P35:S35) -> 109256 | U35: =O35+T35 -> 324436 | V35: 37692936 | W35: 14581257 | X35: -23111679 | Y35: 19470854 | Z35: =Y35/AD35 -> 3916.8888 | AA35: 0 | AB35: 0 | AC35: 3183 | AD35: 4971 | AE35: 0 | AF35: 2126136.3 | AG35: 5017677.3 | AH35: =AF35-AG35 -> -2891541 | AI35: =AH35/D35 -> -96384.699 | AJ35: 30 | AK35: 702 | AL35: TRUE | AM35: =IF('MANOVA '!M77, 1, 0) -> 0
A36: 10 | B36: 199 | C36: 0.3 | D36: 30 | E36: 15 | F36: 3 | G36: 3 | H36: 15 | I36: 45.06 | J36: 49.35 | K36: 88811 | L36: 94249 | M36: 27163 | N36: 12163 | O36: =SUM(K36:N36) -> 222386 | P36: 25488 | Q36: 39197 | R36: 3091 | S36: 37996 | T36: =SUM(P36:S36) -> 105772 | U36: =O36+T36 -> 328158 | V36: 30815602 | W36: 16406563 | X36: -14409038 | Y36: 8804939.1 | Z36: =Y36/AD36 -> 3480.2131 | AA36: 0 | AB36: 0 | AC36: 3158 | AD36: 2530 | AE36: 0 | AF36: 4571570.8 | AG36: 5017677.3 | AH36: =AF36-AG36 -> -446106.54 | AI36: =AH36/D36 -> -14870.218 | AJ36: 30 | AK36: 467 | AL36: TRUE | AM36: =IF('MANOVA '!M78, 1, 0) -> 0
A37: 10 | B37: 199 | C37: 0.3 | D37: 30 | E37: 15 | F37: 3 | G37: 3 | H37: 15 | I37: 90.12 | J37: 98.7 | K37: 88241 | L37: 93888 | M37: 26924 | N37: 12090 | O37: =SUM(K37:N37) -> 221143 | P37: 25706 | Q37: 39128 | R37: 2996 | S37: 38060 | T37: =SUM(P37:S37) -> 105890 | U37: =O37+T37 -> 327033 | V37: 30116482 | W37: 24414508 | X37: -5701973.8 | Y37: 9287902.3 | Z37: =Y37/AD37 -> 3658.0947 | AA37: 0 | AB37: 0 | AC37: 3167 | AD37: 2539 | AE37: 0 | AF37: 6390578.4 | AG37: 5017677.3 | AH37: =AF37-AG37 -> 1372901.1 | AI37: =AH37/D37 -> 45763.371 | AJ37: 30 | AK37: 516 | AL37: TRUE | AM37: =IF('MANOVA '!M79, 1, 0) -> 0
A38: 10 | B38: 199 | C38: 0.3 | D38: 30 | E38: 15 | F38: 3 | G38: 1 | H38: 30 | I38: 45.06 | J38: 49.35 | K38: 89114 | L38: 95975 | M38: 27470 | N38: 12204 | O38: =SUM(K38:N38) -> 224763 | P38: 25616 | Q38: 39818 | R38: 3170 | S38: 37961 | T38: =SUM(P38:S38) -> 106565 | U38: =O38+T38 -> 331328 | V38: 40575933 | W38: 16958971 | X38: -23616962 | Y38: 18482479 | Z38: =Y38/AD38 -> 3700.9369 | AA38: 0 | AB38: 0 | AC38: 3174 | AD38: 4994 | AE38: 0 | AF38: 4640105.8 | AG38: 5017677.3 | AH38: =AF38-AG38 -> -377571.55 | AI38: =AH38/D38 -> -12585.718 | AJ38: 30 | AK38: 432 | AL38: TRUE | AM38: =IF('MANOVA '!M80, 1, 0) -> 0
A39: 10 | B39: 198 | C39: 0.3 | D39: 30 | E39: 15 | F39: 3 | G39: 1 | H39: 30 | I39: 90.12 | J39: 98.7 | K39: 80515 | L39: 96386 | M39: 26993 | N39: 12175 | O39: =SUM(K39:N39) -> 216069 | P39: 26499 | Q39: 41236 | R39: 3217 | S39: 38272 | T39: =SUM(P39:S39) -> 109224 | U39: =O39+T39 -> 325293 | V39: 39163977 | W39: 24425639 | X39: -14738338 | Y39: 18587756 | Z39: =Y39/AD39 -> 3740.7437 | AA39: 0 | AB39: 0 | AC39: 3171 | AD39: 4969 | AE39: 0 | AF39: 8418686.3 | AG39: 5017677.3 | AH39: =AF39-AG39 -> 3401009 | AI39: =AH39/D39 -> 113366.97 | AJ39: 30 | AK39: 533 | AL39: TRUE | AM39: =IF('MANOVA '!M81, 1, 0) -> 0
A40: 10 | B40: 200 | C40: 0.3 | D40: 30 | E40: 15 | F40: 3 | G40: 1 | H40: 15 | I40: 45.06 | J40: 49.35 | K40: 87494 | L40: 92499 | M40: 26689 | N40: 12258 | O40: =SUM(K40:N40) -> 218940 | P40: 24830 | Q40: 38197 | R40: 2950 | S40: 38166 | T40: =SUM(P40:S40) -> 104143 | U40: =O40+T40 -> 323083 | V40: 29922414 | W40: 13736600 | X40: -16185814 | Y40: 9065336.7 | Z40: =Y40/AD40 -> 3556.4287 | AA40: 0 | AB40: 0 | AC40: 3205 | AD40: 2549 | AE40: 0 | AF40: 2713846.8 | AG40: 5017677.3 | AH40: =AF40-AG40 -> -2303830.5 | AI40: =AH40/D40 -> -76794.349 | AJ40: 30 | AK40: 558 | AL40: TRUE | AM40: =IF('MANOVA '!M82, 1, 0) -> 0
A41: 10 | B41: 199 | C41: 0.3 | D41: 30 | E41: 15 | F41: 3 | G41: 1 | H41: 15 | I41: 90.12 | J41: 98.7 | K41: 88557 | L41: 94129 | M41: 26733 | N41: 12268 | O41: =SUM(K41:N41) -> 221687 | P41: 25478 | Q41: 39343 | R41: 3023 | S41: 38104 | T41: =SUM(P41:S41) -> 105948 | U41: =O41+T41 -> 327635 | V41: 29641491 | W41: 20050418 | X41: -9591073.9 | Y41: 9628718.7 | Z41: =Y41/AD41 -> 3786.362 | AA41: 0 | AB41: 0 | AC41: 3178 | AD41: 2543 | AE41: 0 | AF41: 4589632.9 | AG41: 5017677.3 | AH41: =AF41-AG41 -> -428044.45 | AI41: =AH41/D41 -> -14268.148 | AJ41: 30 | AK41: 598 | AL41: TRUE | AM41: =IF('MANOVA '!M83, 1, 0) -> 0
A42: 10 | B42: 197 | C42: 0.3 | D42: 30 | E42: 15 | F42: 1 | G42: 3 | H42: 30 | I42: 45.06 | J42: 49.35 | K42: 71868 | L42: 97763 | M42: 27667 | N42: 12124 | O42: =SUM(K42:N42) -> 209422 | P42: 27088 | Q42: 41844 | R42: 3204 | S42: 38198 | T42: =SUM(P42:S42) -> 110334 | U42: =O42+T42 -> 319756 | V42: 40000490 | W42: 16564384 | X42: -23436107 | Y42: 19923126 | Z42: =Y42/AD42 -> 4083.4445 | AA42: 0 | AB42: 0 | AC42: 3133 | AD42: 4879 | AE42: 0 | AF42: 4161460.3 | AG42: 5017677.3 | AH42: =AF42-AG42 -> -856217.01 | AI42: =AH42/D42 -> -28540.567 | AJ42: 30 | AK42: 417 | AL42: TRUE | AM42: =IF('MANOVA '!M84, 1, 0) -> 0
A43: 10 | B43: 200 | C43: 0.3 | D43: 30 | E43: 15 | F43: 1 | G43: 3 | H43: 30 | I43: 90.12 | J43: 98.7 | K43: 88102 | L43: 94813 | M43: 27183 | N43: 12236 | O43: =SUM(K43:N43) -> 222334 | P43: 25005 | Q43: 39144 | R43: 3106 | S43: 38174 | T43: =SUM(P43:S43) -> 105429 | U43: =O43+T43 -> 327763 | V43: 38824222 | W43: 19433319 | X43: -19390903 | Y43: 19366660 | Z43: =Y43/AD43 -> 3892.796 | AA43: 0 | AB43: 0 | AC43: 3186 | AD43: 4975 | AE43: 0 | AF43: 3373422.1 | AG43: 5017677.3 | AH43: =AF43-AG43 -> -1644255.2 | AI43: =AH43/D43 -> -54808.508 | AJ43: 30 | AK43: 568 | AL43: TRUE | AM43: =IF('MANOVA '!M85, 1, 0) -> 0
A44: 10 | B44: 199 | C44: 0.3 | D44: 30 | E44: 15 | F44: 1 | G44: 3 | H44: 15 | I44: 45.06 | J44: 49.35 | K44: 88139 | L44: 94040 | M44: 26817 | N44: 12167 | O44: =SUM(K44:N44) -> 221163 | P44: 25707 | Q44: 39446 | R44: 3101 | S44: 38240 | T44: =SUM(P44:S44) -> 106494 | U44: =O44+T44 -> 327657 | V44: 31148158 | W44: 15758629 | X44: -15389530 | Y44: 9775615.8 | Z44: =Y44/AD44 -> 3940.1918 | AA44: 0 | AB44: 0 | AC44: 3187 | AD44: 2481 | AE44: 0 | AF44: 4754894 | AG44: 5017677.3 | AH44: =AF44-AG44 -> -262783.34 | AI44: =AH44/D44 -> -8759.4446 | AJ44: 30 | AK44: 458 | AL44: TRUE | AM44: =IF('MANOVA '!M86, 1, 0) -> 0
A45: 10 | B45: 203 | C45: 0.3 | D45: 30 | E45: 15 | F45: 1 | G45: 3 | H45: 15 | I45: 90.12 | J45: 98.7 | K45: 74854 | L45: 99760 | M45: 26494 | N45: 12262 | O45: =SUM(K45:N45) -> 213370 | P45: 22905 | Q45: 35240 | R45: 3651 | S45: 38262 | T45: =SUM(P45:S45) -> 100058 | U45: =O45+T45 -> 313428 | V45: 30885050 | W45: 24739696 | X45: -6145353.9 | Y45: 9960784.9 | Z45: =Y45/AD45 -> 3930.8543 | AA45: 0 | AB45: 0 | AC45: 3229 | AD45: 2534 | AE45: 0 | AF45: 7766409.1 | AG45: 5017677.3 | AH45: =AF45-AG45 -> 2748731.8 | AI45: =AH45/D45 -> 91624.394 | AJ45: 30 | AK45: 474 | AL45: TRUE | AM45: =IF('MANOVA '!M87, 1, 0) -> 0
... A97: 10 | B97: 159 | C97: 0.3 | D97: 50 | E97: 10 | F97: 1 | G97: 1 | H97: 15 | I97: 90.12 | J97: 98.7 | K97: 59639 | L97: 79327 | M97: 31850 | N97: 11217 | O97: =SUM(K97:N97) -> 182033 | P97: 6533 | Q97: 48208 | R97: 4630 | S97: 37475 | T97: =SUM(P97:S97) -> 96846 | U97: =O97+T97 -> 278879 | V97: 26576048 | W97: 33259099 | X97: 6683051 | Y97: 8536772.4 | Z97: =Y97/AD97 -> 5164.4116 | AA97: 0 | AB97: 0 | AC97: 2497 | AD97: 1653 | AE97: 0 | AF97: 7565291.5 | AG97: 5695648 | AH97: =AF97-AG97 -> 1869643.5 | AI97: =AH97/D97 -> 37392.871 | AJ97: 50 | AK97: 569 | AL97: TRUE | AM97: =IF('MANOVA '!M139, 1, 0) -> 0
A98: 10 | B98: 188 | C98: 0.4 | D98: 5 | E98: 15 | F98: 3 | G98: 3 | H98: 30 | I98: 45.06 | J98: 49.35 | K98: 73201 | L98: 80143 | M98: 27706 | N98: 9613 | O98: =SUM(K98:N98) -> 190663 | P98: 4666 | Q98: 35978 | R98: 3883 | S98: 29728 | T98: =SUM(P98:S98) -> 74255 | U98: =O98+T98 -> 264918 | V98: 10806189 | W98: 4562060.6 | X98: -6244128.8 | Y98: 7755040.3 | Z98: =Y98/AD98 -> 4398.775 | AA98: 1.6954165e+08 | AB98: =AA98/AE98 -> 95570.267 | AC98: 421 | AD98: 1763 | AE98: 1774 | AF98: 1189562.9 | AG98: 836279.55 | AH98: =AF98-AG98 -> 353283.39 | AI98: =AH98/D98 -> 70656.678 | AJ98: 5 | AK98: 0 | AL98: TRUE | AM98: =IF('MANOVA '!M140, 1, 0) -> 0
A99: 10 | B99: 188 | C99: 0.4 | D99: 5 | E99: 15 | F99: 3 | G99: 3 | H99: 30 | I99: 90.12 | J99: 98.7 | K99: 72883 | L99: 80273 | M99: 27462 | N99: 9476 | O99: =SUM(K99:N99) -> 190094 | P99: 4724 | Q99: 36180 | R99: 3820 | S99: 29420 | T99: =SUM(P99:S99) -> 74144 | U99: =O99+T99 -> 264238 | V99: 10817229 | W99: 8287841.6 | X99: -2529386.9 | Y99: 8284156.9 | Z99: =Y99/AD99 -> 4706.9073 | AA99: 3.568204e+08 | AB99: =AA99/AE99 -> 190304.21 | AC99: 442 | AD99: 1760 | AE99: 1875 | AF99: 2379125.9 | AG99: 836279.55 | AH99: =AF99-AG99 -> 1542846.3 | AI99: =AH99/D99 -> 308569.27 | AJ99: 5 | AK99: 0 | AL99: TRUE | AM99: =IF('MANOVA '!M141, 1, 0) -> 0
A100: 10 | B100: 188 | C100: 0.4 | D100: 5 | E100: 15 | F100: 3 | G100: 3 | H100: 15 | I100: 45.06 | J100: 49.35 | K100: 82438 | L100: 84252 | M100: 27700 | N100: 11084 | O100: =SUM(K100:N100) -> 205474 | P100: 5242 | Q100: 41061 | R100: 4030 | S100: 35079 | T100: =SUM(P100:S100) -> 85412 | U100: =O100+T100 -> 290886 | V100: 10738477 | W100: 4880490.8 | X100: -5857986.3 | Y100: 7146329.5 | Z100: =Y100/AD100 -> 4578.0458 | AA100: 53834769 | AB100: =AA100/AE100 -> 145107.2 | AC100: 396 | AD100: 1561 | AE100: 371 | AF100: 2225737.4 | AG100: 836279.55 | AH100: =AF100-AG100 -> 1389457.9 | AI100: =AH100/D100 -> 277891.57 | AJ100: 5 | AK100: 10 | AL100: TRUE | AM100: =IF('MANOVA '!M142, 1, 0) -> 0
A101: 10 | B101: 188 | C101: 0.4 | D101: 5 | E101: 15 | F101: 3 | G101: 3 | H101: 15 | I101: 90.12 | J101: 98.7 | K101: 82438 | L101: 84252 | M101: 27700 | N101: 11084 | O101: =SUM(K101:N101) -> 205474 | P101: 5242 | Q101: 41061 | R101: 4030 | S101: 35079 | T101: =SUM(P101:S101) -> 85412 | U101: =O101+T101 -> 290886 | V101: 10738477 | W101: 8924702.1 | X101: -1813775 | Y101: 8124390.9 | Z101: =Y101/AD101 -> 5204.6066 | AA101: 1.0766954e+08 | AB101: =AA101/AE101 -> 290214.39 | AC101: 396 | AD101: 1561 | AE101: 371 | AF101: 4451474.8 | AG101: 836279.55 | AH101: =AF101-AG101 -> 3615195.3 | AI101: =AH101/D101 -> 723039.06 | AJ101: 5 | AK101: 10 | AL101: TRUE | AM101: =IF('MANOVA '!M143, 1, 0) -> 0
A102: 10 | B102: 188 | C102: 0.4 | D102: 5 | E102: 15 | F102: 3 | G102: 1 | H102: 30 | I102: 45.06 | J102: 49.35 | K102: 73241 | L102: 79490 | M102: 27740 | N102: 9495 | O102: =SUM(K102:N102) -> 189966 | P102: 4638 | Q102: 35785 | R102: 3920 | S102: 29036 | T102: =SUM(P102:S102) -> 73379 | U102: =O102+T102 -> 263345 | V102: 10735529 | W102: 4471817.9 | X102: -6263711.5 | Y102: 7816405.8 | Z102: =Y102/AD102 -> 4411.0642 | AA102: 1.9868573e+08 | AB102: =AA102/AE102 -> 101629.53 | AC102: 403 | AD102: 1772 | AE102: 1955 | AF102: 1069239.4 | AG102: 836279.55 | AH102: =AF102-AG102 -> 232959.85 | AI102: =AH102/D102 -> 46591.97 | AJ102: 5 | AK102: 0 | AL102: TRUE | AM102: =IF('MANOVA '!M144, 1, 0) -> 0
A103: 10 | B103: 188 | C103: 0.4 | D103: 5 | E103: 15 | F103: 3 | G103: 1 | H103: 30 | I103: 90.12 | J103: 98.7 | K103: 73241 | L103: 79490 | M103: 27740 | N103: 9495 | O103: =SUM(K103:N103) -> 189966 | P103: 4638 | Q103: 35785 | R103: 3920 | S103: 29036 | T103: =SUM(P103:S103) -> 73379 | U103: =O103+T103 -> 263345 | V103: 10735529 | W103: 8107356.3 | X103: -2628173.1 | Y103: 8701447.4 | Z103: =Y103/AD103 -> 4910.5234 | AA103: 3.9737145e+08 | AB103: =AA103/AE103 -> 203259.05 | AC103: 403 | AD103: 1772 | AE103: 1955 | AF103: 2138478.8 | AG103: 836279.55 | AH103: =AF103-AG103 -> 1302199.3 | AI103: =AH103/D103 -> 260439.85 | AJ103: 5 | AK103: 0 | AL103: TRUE | AM103: =IF('MANOVA '!M145, 1, 0) -> 0
A104: 10 | B104: 188 | C104: 0.4 | D104: 5 | E104: 15 | F104: 3 | G104: 1 | H104: 15 | I104: 45.06 | J104: 49.35 | K104: 82157 | L104: 84042 | M104: 27920 | N104: 10997 | O104: =SUM(K104:N104) -> 205116 | P104: 5230 | Q104: 41124 | R104: 4073 | S104: 34867 | T104: =SUM(P104:S104) -> 85294 | U104: =O104+T104 -> 290410 | V104: 10823878 | W104: 4876056.5 | X104: -5947821.5 | Y104: 6486029.2 | Z104: =Y104/AD104 -> 4089.5518 | AA104: 63274040 | AB104: =AA104/AE104 -> 146467.69 | AC104: 347 | AD104: 1586 | AE104: 432 | AF104: 2214695.3 | AG104: 836279.55 | AH104: =AF104-AG104 -> 1378415.8 | AI104: =AH104/D104 -> 275683.15 | AJ104: 5 | AK104: 10 | AL104: TRUE | AM104: =IF('MANOVA '!M146, 1, 0) -> 0
A105: 10 | B105: 188 | C105: 0.4 | D105: 5 | E105: 15 | F105: 3 | G105: 1 | H105: 15 | I105: 90.12 | J105: 98.7 | K105: 82157 | L105: 84042 | M105: 27920 | N105: 10997 | O105: =SUM(K105:N105) -> 205116 | P105: 5230 | Q105: 41124 | R105: 4073 | S105: 34867 | T105: =SUM(P105:S105) -> 85294 | U105: =O105+T105 -> 290410 | V105: 10823878 | W105: 8915833.5 | X105: -1908044.5 | Y105: 6674539 | Z105: =Y105/AD105 -> 4208.4105 | AA105: 1.2654808e+08 | AB105: =AA105/AE105 -> 292935.37 | AC105: 347 | AD105: 1586 | AE105: 432 | AF105: 4429390.6 | AG105: 836279.55 | AH105: =AF105-AG105 -> 3593111.1 | AI105: =AH105/D105 -> 718622.22 | AJ105: 5 | AK105: 10 | AL105: TRUE | AM105: =IF('MANOVA '!M147, 1, 0) -> 0
A106: 10 | B106: 188 | C106: 0.4 | D106: 5 | E106: 15 | F106: 1 | G106: 3 | H106: 30 | I106: 45.06 | J106: 49.35 | K106: 69221 | L106: 79600 | M106: 27121 | N106: 8968 | O106: =SUM(K106:N106) -> 184910 | P106: 4469 | Q106: 34101 | R106: 3734 | S106: 27369 | T106: =SUM(P106:S106) -> 69673 | U106: =O106+T106 -> 254583 | V106: 8788953.8 | W106: 4097841.6 | X106: -4691112.2 | Y106: 7307717.4 | Z106: =Y106/AD106 -> 5515.2584 | AA106: 2.305636e+08 | AB106: =AA106/AE106 -> 98827.09 | AC106: 423 | AD106: 1325 | AE106: 2333 | AF106: 1256818.8 | AG106: 836279.55 | AH106: =AF106-AG106 -> 420539.22 | AI106: =AH106/D106 -> 84107.843 | AJ106: 5 | AK106: 0 | AL106: TRUE | AM106: =IF('MANOVA '!M148, 1, 0) -> 0
A107: 10 | B107: 188 | C107: 0.4 | D107: 5 | E107: 15 | F107: 1 | G107: 3 | H107: 30 | I107: 90.12 | J107: 98.7 | K107: 69221 | L107: 79600 | M107: 27121 | N107: 8968 | O107: =SUM(K107:N107) -> 184910 | P107: 4469 | Q107: 34101 | R107: 3734 | S107: 27369 | T107: =SUM(P107:S107) -> 69673 | U107: =O107+T107 -> 254583 | V107: 8788953.8 | W107: 7359403.7 | X107: -1429550.1 | Y107: 9199320.9 | Z107: =Y107/AD107 -> 6942.8837 | AA107: 4.611272e+08 | AB107: =AA107/AE107 -> 197654.18 | AC107: 423 | AD107: 1325 | AE107: 2333 | AF107: 2513637.5 | AG107: 836279.55 | AH107: =AF107-AG107 -> 1677358 | AI107: =AH107/D107 -> 335471.6 | AJ107: 5 | AK107: 0 | AL107: TRUE | AM107: =IF('MANOVA '!M149, 1, 0) -> 0
A108: 10 | B108: 188 | C108: 0.4 | D108: 5 | E108: 15 | F108: 1 | G108: 3 | H108: 15 | I108: 45.06 | J108: 49.35 | K108: 80866 | L108: 83389 | M108: 27588 | N108: 10862 | O108: =SUM(K108:N108) -> 202705 | P108: 5210 | Q108: 40675 | R108: 3925 | S108: 34534 | T108: =SUM(P108:S108) -> 84344 | U108: =O108+T108 -> 287049 | V108: 9358106.3 | W108: 4350561.7 | X108: -5007544.6 | Y108: 6012871.7 | Z108: =Y108/AD108 -> 4621.7308 | AA108: 63408637 | AB108: =AA108/AE108 -> 115079.2 | AC108: 373 | AD108: 1301 | AE108: 551 | AF108: 2200250 | AG108: 836279.55 | AH108: =AF108-AG108 -> 1363970.4 | AI108: =AH108/D108 -> 272794.09 | AJ108: 5 | AK108: 11 | AL108: TRUE | AM108: =IF('MANOVA '!M150, 1, 0) -> 0
A109: 10 | B109: 188 | C109: 0.4 | D109: 5 | E109: 15 | F109: 1 | G109: 3 | H109: 15 | I109: 90.12 | J109: 98.7 | K109: 80866 | L109: 83389 | M109: 27588 | N109: 10862 | O109: =SUM(K109:N109) -> 202705 | P109: 5210 | Q109: 40675 | R109: 3925 | S109: 34534 | T109: =SUM(P109:S109) -> 84344 | U109: =O109+T109 -> 287049 | V109: 9358106.3 | W109: 7864843.9 | X109: -1493262.4 | Y109: 6440741 | Z109: =Y109/AD109 -> 4950.608 | AA109: 1.2681727e+08 | AB109: =AA109/AE109 -> 230158.39 | AC109: 373 | AD109: 1301 | AE109: 551 | AF109: 4400500 | AG109: 836279.55 | AH109: =AF109-AG109 -> 3564220.4 | AI109: =AH109/D109 -> 712844.09 | AJ109: 5 | AK109: 11 | AL109: TRUE | AM109: =IF('MANOVA '!M151, 1, 0) -> 0
... A129: 10 | B129: 128 | C129: 0.4 | D129: 5 | E129: 10 | F129: 1 | G129: 1 | H129: 15 | I129: 90.12 | J129: 98.7 | K129: 73081 | L129: 55052 | M129: 34069 | N129: 9798 | O129: =SUM(K129:N129) -> 172000 | P129: 21322 | Q129: 28554 | R129: 8273 | S129: 33305 | T129: =SUM(P129:S129) -> 91454 | U129: =O129+T129 -> 263454 | V129: 6627479.4 | W129: 5987336.2 | X129: -640143.22 | Y129: 4093954.9 | Z129: =Y129/AD129 -> 4839.1902 | AA129: 1.1196898e+08 | AB129: =AA129/AE129 -> 242357.1 | AC129: 283 | AD129: 846 | AE129: 462 | AF129: 2453578.5 | AG129: 569564.8 | AH129: =AF129-AG129 -> 1884013.7 | AI129: =AH129/D129 -> 376802.74 | AJ129: 5 | AK129: 9 | AL129: TRUE | AM129: =IF('MANOVA '!M171, 1, 0) -> 0
A130: 10 | B130: 198 | C130: 0.4 | D130: 30 | E130: 15 | F130: 3 | G130: 3 | H130: 30 | I130: 45.06 | J130: 49.35 | K130: 81327 | L130: 98501 | M130: 27633 | N130: 12131 | O130: =SUM(K130:N130) -> 219592 | P130: 26339 | Q130: 41968 | R130: 3537 | S130: 38051 | T130: =SUM(P130:S130) -> 109895 | U130: =O130+T130 -> 329487 | V130: 39851834 | W130: 14738334 | X130: -25113500 | Y130: 18435799 | Z130: =Y130/AD130 -> 3707.9242 | AA130: 0 | AB130: 0 | AC130: 3160 | AD130: 4972 | AE130: 0 | AF130: 5063276.2 | AG130: 5017677.3 | AH130: =AF130-AG130 -> 45598.877 | AI130: =AH130/D130 -> 1519.9626 | AJ130: 30 | AK130: 488 | AL130: TRUE | AM130: =IF('MANOVA '!M172, 1, 0) -> 0
A131: 10 | B131: 198 | C131: 0.4 | D131: 30 | E131: 15 | F131: 3 | G131: 3 | H131: 30 | I131: 90.12 | J131: 98.7 | K131: 81327 | L131: 98501 | M131: 27633 | N131: 12131 | O131: =SUM(K131:N131) -> 219592 | P131: 26339 | Q131: 41968 | R131: 3537 | S131: 38051 | T131: =SUM(P131:S131) -> 109895 | U131: =O131+T131 -> 329487 | V131: 39851834 | W131: 24458990 | X131: -15392844 | Y131: 18435799 | Z131: =Y131/AD131 -> 3707.9242 | AA131: 0 | AB131: 0 | AC131: 3160 | AD131: 4972 | AE131: 0 | AF131: 10126552 | AG131: 5017677.3 | AH131: =AF131-AG131 -> 5108875.1 | AI131: =AH131/D131 -> 170295.84 | AJ131: 30 | AK131: 488 | AL131: TRUE | AM131: =IF('MANOVA '!M173, 1, 0) -> 0
A132: 10 | B132: 199 | C132: 0.4 | D132: 30 | E132: 15 | F132: 3 | G132: 3 | H132: 15 | I132: 45.06 | J132: 49.35 | K132: 88465 | L132: 95056 | M132: 27040 | N132: 12179 | O132: =SUM(K132:N132) -> 222740 | P132: 25609 | Q132: 39900 | R132: 3255 | S132: 38124 | T132: =SUM(P132:S132) -> 106888 | U132: =O132+T132 -> 329628 | V132: 30410779 | W132: 14022267 | X132: -16388512 | Y132: 9784023.3 | Z132: =Y132/AD132 -> 3853.4948 | AA132: 0 | AB132: 0 | AC132: 3179 | AD132: 2539 | AE132: 0 | AF132: 5283522.7 | AG132: 5017677.3 | AH132: =AF132-AG132 -> 265845.44 | AI132: =AH132/D132 -> 8861.5148 | AJ132: 30 | AK132: 507 | AL132: TRUE | AM132: =IF('MANOVA '!M174, 1, 0) -> 0
A133: 10 | B133: 199 | C133: 0.4 | D133: 30 | E133: 15 | F133: 3 | G133: 3 | H133: 15 | I133: 90.12 | J133: 98.7 | K133: 88465 | L133: 95056 | M133: 27040 | N133: 12179 | O133: =SUM(K133:N133) -> 222740 | P133: 25609 | Q133: 39900 | R133: 3255 | S133: 38124 | T133: =SUM(P133:S133) -> 106888 | U133: =O133+T133 -> 329628 | V133: 30410779 | W133: 23026856 | X133: -7383922.6 | Y133: 9784023.3 | Z133: =Y133/AD133 -> 3853.4948 | AA133: 0 | AB133: 0 | AC133: 3179 | AD133: 2539 | AE133: 0 | AF133: 10567045 | AG133: 5017677.3 | AH133: =AF133-AG133 -> 5549368.2 | AI133: =AH133/D133 -> 184978.94 | AJ133: 30 | AK133: 507 | AL133: TRUE | AM133: =IF('MANOVA '!M175, 1, 0) -> 0
A134: 10 | B134: 200 | C134: 0.4 | D134: 30 | E134: 15 | F134: 3 | G134: 1 | H134: 30 | I134: 45.06 | J134: 49.35 | K134: 88664 | L134: 95601 | M134: 27230 | N134: 12303 | O134: =SUM(K134:N134) -> 223798 | P134: 24905 | Q134: 40165 | R134: 3485 | S134: 38161 | T134: =SUM(P134:S134) -> 106716 | U134: =O134+T134 -> 330514 | V134: 39128362 | W134: 11827969 | X134: -27300393 | Y134: 19211093 | Z134: =Y134/AD134 -> 3817.7847 | AA134: 0 | AB134: 0 | AC134: 3210 | AD134: 5032 | AE134: 0 | AF134: 3290091.4 | AG134: 5017677.3 | AH134: =AF134-AG134 -> -1727585.9 | AI134: =AH134/D134 -> -57586.197 | AJ134: 30 | AK134: 617 | AL134: TRUE | AM134: =IF('MANOVA '!M176, 1, 0) -> 0
A135: 10 | B135: 200 | C135: 0.4 | D135: 30 | E135: 15 | F135: 3 | G135: 1 | H135: 30 | I135: 90.12 | J135: 98.7 | K135: 88664 | L135: 95601 | M135: 27230 | N135: 12303 | O135: =SUM(K135:N135) -> 223798 | P135: 24905 | Q135: 40165 | R135: 3485 | S135: 38161 | T135: =SUM(P135:S135) -> 106716 | U135: =O135+T135 -> 330514 | V135: 39128362 | W135: 18638261 | X135: -20490101 | Y135: 19211093 | Z135: =Y135/AD135 -> 3817.7847 | AA135: 0 | AB135: 0 | AC135: 3210 | AD135: 5032 | AE135: 0 | AF135: 6580182.8 | AG135: 5017677.3 | AH135: =AF135-AG135 -> 1562505.5 | AI135: =AH135/D135 -> 52083.516 | AJ135: 30 | AK135: 617 | AL135: TRUE | AM135: =IF('MANOVA '!M177, 1, 0) -> 0
A136: 10 | B136: 199 | C136: 0.4 | D136: 30 | E136: 15 | F136: 3 | G136: 1 | H136: 15 | I136: 45.06 | J136: 49.35 | K136: 88564 | L136: 94855 | M136: 27132 | N136: 12181 | O136: =SUM(K136:N136) -> 222732 | P136: 25528 | Q136: 39923 | R136: 3287 | S136: 38211 | T136: =SUM(P136:S136) -> 106949 | U136: =O136+T136 -> 329681 | V136: 29824650 | W136: 13121797 | X136: -16702853 | Y136: 9567914.8 | Z136: =Y136/AD136 -> 3765.4132 | AA136: 0 | AB136: 0 | AC136: 3188 | AD136: 2541 | AE136: 0 | AF136: 5098514.9 | AG136: 5017677.3 | AH136: =AF136-AG136 -> 80837.628 | AI136: =AH136/D136 -> 2694.5876 | AJ136: 30 | AK136: 566 | AL136: TRUE | AM136: =IF('MANOVA '!M178, 1, 0) -> 0
A137: 10 | B137: 199 | C137: 0.4 | D137: 30 | E137: 15 | F137: 3 | G137: 1 | H137: 15 | I137: 90.12 | J137: 98.7 | K137: 88564 | L137: 94855 | M137: 27132 | N137: 12181 | O137: =SUM(K137:N137) -> 222732 | P137: 25528 | Q137: 39923 | R137: 3287 | S137: 38211 | T137: =SUM(P137:S137) -> 106949 | U137: =O137+T137 -> 329681 | V137: 29824650 | W137: 21225917 | X137: -8598733.5 | Y137: 9567914.8 | Z137: =Y137/AD137 -> 3765.4132 | AA137: 0 | AB137: 0 | AC137: 3188 | AD137: 2541 | AE137: 0 | AF137: 10197030 | AG137: 5017677.3 | AH137: =AF137-AG137 -> 5179352.6 | AI137: =AH137/D137 -> 172645.09 | AJ137: 30 | AK137: 566 | AL137: TRUE | AM137: =IF('MANOVA '!M179, 1, 0) -> 0
A138: 10 | B138: 203 | C138: 0.4 | D138: 30 | E138: 15 | F138: 1 | G138: 3 | H138: 30 | I138: 45.06 | J138: 49.35 | K138: 75689 | L138: 102882 | M138: 26894 | N138: 12339 | O138: =SUM(K138:N138) -> 217804 | P138: 22854 | Q138: 36886 | R138: 4278 | S138: 38183 | T138: =SUM(P138:S138) -> 102201 | U138: =O138+T138 -> 320005 | V138: 38838884 | W138: 10438460 | X138: -28400424 | Y138: 19792476 | Z138: =Y138/AD138 -> 3926.2995 | AA138: 0 | AB138: 0 | AC138: 3246 | AD138: 5041 | AE138: 0 | AF138: 1503045.2 | AG138: 5017677.3 | AH138: =AF138-AG138 -> -3514632.1 | AI138: =AH138/D138 -> -117154.4 | AJ138: 30 | AK138: 648 | AL138: TRUE | AM138: =IF('MANOVA '!M180, 1, 0) -> 0
A139: 10 | B139: 203 | C139: 0.4 | D139: 30 | E139: 15 | F139: 1 | G139: 3 | H139: 30 | I139: 90.12 | J139: 98.7 | K139: 75689 | L139: 102882 | M139: 26894 | N139: 12339 | O139: =SUM(K139:N139) -> 217804 | P139: 22854 | Q139: 36886 | R139: 4278 | S139: 38183 | T139: =SUM(P139:S139) -> 102201 | U139: =O139+T139 -> 320005 | V139: 38838884 | W139: 15859242 | X139: -22979642 | Y139: 19792476 | Z139: =Y139/AD139 -> 3926.2995 | AA139: 0 | AB139: 0 | AC139: 3246 | AD139: 5041 | AE139: 0 | AF139: 3006090.5 | AG139: 5017677.3 | AH139: =AF139-AG139 -> -2011586.8 | AI139: =AH139/D139 -> -67052.895 | AJ139: 30 | AK139: 648 | AL139: TRUE | AM139: =IF('MANOVA '!M181, 1, 0) -> 0
A140: 10 | B140: 197 | C140: 0.4 | D140: 30 | E140: 15 | F140: 1 | G140: 3 | H140: 15 | I140: 45.06 | J140: 49.35 | K140: 71129 | L140: 96016 | M140: 27178 | N140: 12126 | O140: =SUM(K140:N140) -> 206449 | P140: 27347 | Q140: 42234 | R140: 3392 | S140: 38378 | T140: =SUM(P140:S140) -> 111351 | U140: =O140+T140 -> 317800 | V140: 27899510 | W140: 10493749 | X140: -17405761 | Y140: 10497374 | Z140: =Y140/AD140 -> 4274.175 | AA140: 0 | AB140: 0 | AC140: 3161 | AD140: 2456 | AE140: 0 | AF140: 2219870.1 | AG140: 5017677.3 | AH140: =AF140-AG140 -> -2797807.2 | AI140: =AH140/D140 -> -93260.239 | AJ140: 30 | AK140: 643 | AL140: TRUE | AM140: =IF('MANOVA '!M182, 1, 0) -> 0
A141: 10 | B141: 197 | C141: 0.4 | D141: 30 | E141: 15 | F141: 1 | G141: 3 | H141: 15 | I141: 90.12 | J141: 98.7 | K141: 71129 | L141: 96016 | M141: 27178 | N141: 12126 | O141: =SUM(K141:N141) -> 206449 | P141: 27347 | Q141: 42234 | R141: 3392 | S141: 38378 | T141: =SUM(P141:S141) -> 111351 | U141: =O141+T141 -> 317800 | V141: 27899510 | W141: 15969820 | X141: -11929690 | Y141: 10497374 | Z141: =Y141/AD141 -> 4274.175 | AA141: 0 | AB141: 0 | AC141: 3161 | AD141: 2456 | AE141: 0 | AF141: 4439740.3 | AG141: 5017677.3 | AH141: =AF141-AG141 -> -577937.02 | AI141: =AH141/D141 -> -19264.567 | AJ141: 30 | AK141: 643 | AL141: TRUE | AM141: =IF('MANOVA '!M183, 1, 0) -> 0
... A193: 10 | B193: 159 | C193: 0.4 | D193: 50 | E193: 10 | F193: 1 | G193: 1 | H193: 15 | I193: 90.12 | J193: 98.7 | K193: 59578 | L193: 79467 | M193: 31679 | N193: 11163 | O193: =SUM(K193:N193) -> 181887 | P193: 6498 | Q193: 47985 | R193: 4636 | S193: 37332 | T193: =SUM(P193:S193) -> 96451 | U193: =O193+T193 -> 278338 | V193: 26041105 | W193: 28336542 | X193: 2295437.5 | Y193: 9149276.4 | Z193: =Y193/AD193 -> 4641.9464 | AA193: 0 | AB193: 0 | AC193: 2468 | AD193: 1971 | AE193: 0 | AF193: 12225992 | AG193: 5695648 | AH193: =AF193-AG193 -> 6530344 | AI193: =AH193/D193 -> 130606.88 | AJ193: 50 | AK193: 678 | AL193: TRUE | AM193: =IF('MANOVA '!M235, 1, 0) -> 0

Sheet Original
A1: seed | B1: cycle | C1: investment_rotation_years | D1: nursery_count | E1: police_count | F1: member_count | G1: investor_count | H1: exotic_price_per_bdft | I1: native_price_per_bdft | J1: investor_percent_earning_share | K1: length(trees where ((each.type = NATIVE) and (each.state = SEEDLING))) | L1: length(trees where ((each.type = NATIVE) and (each.state = SAPLING))) | M1: length(trees where ((each.type = NATIVE) and (each.state = POLE))) | N1: length(trees where ((each.type = NATIVE) and (each.state = ADULT))) | O1: length(trees where ((each.type = EXOTIC) and (each.state = SEEDLING))) | P1: length(trees where ((each.type = EXOTIC) and (each.state = SAPLING))) | Q1: length(trees where ((each.type = EXOTIC) and (each.state = POLE))) | R1: length(trees where ((each.type = EXOTIC) and (each.state = ADULT))) | S1: management_running_cost | T1: ITP_running_earning | U1: net_running_earning | V1: m_partners_earning | W1: m_independent_earning | X1: own_laborer | Y1: member_laborer | Z1: independent_laborer | AA1: investor_total_profit | AB1: total_investment_cost | AC1: net investor profit | AD1: average net investor profit | AE1: total_investments | AF1: inv_harvested_trees | AG1: with_investment
A2: 10 | B2: 193 | C2: 15 | D2: 3 | E2: 3 | F2: 30 | G2: 5 | H2: 45.06 | I2: 49.35 | J2: 0.3 | K2: 56130 | L2: 96236 | M2: 28211 | N2: 9944 | O2: 29180 | P2: 32631 | Q2: 3480 | R2: 31158 | S2: 10795377 | T2: 4787166.8 | U2: -6008210.7 | V2: 10515649 | W2: 1.4950462e+08 | X2: 724 | Y2: 1730 | Z2: 1579 | AA2: 942069.87 | AB2: 836279.55 | AC2: =AA2-AB2 -> 105790.32 | AD2: =AC2/G2 -> 21158.065 | AE2: 5 | AF2: 0 | AG2: TRUE
A3: 10 | B3: 188 | C3: 15 | D3: 3 | E3: 3 | F3: 30 | G3: 5 | H3: 90.12 | I3: 98.7 | J3: 0.3 | K3: 76141 | L3: 84920 | M3: 28577 | N3: 9580 | O3: 4767 | P3: 35386 | Q3: 3891 | R3: 28179 | S3: 10797015 | T3: 8570550.9 | U3: -2226463.7 | V3: 12649332 | W3: 4.7381087e+08 | X3: 583 | Y3: 1635 | Z3: 1907 | AA3: 1782884.6 | AB3: 836279.55 | AC3: =AA3-AB3 -> 946605.07 | AD3: =AC3/G3 -> 189321.01 | AE3: 5 | AF3: 0 | AG3: TRUE
A4: 10 | B4: 193 | C4: 15 | D4: 3 | E4: 3 | F4: 15 | G4: 5 | H4: 45.06 | I4: 49.35 | J4: 0.3 | K4: 60779 | L4: 96973 | M4: 26668 | N4: 10965 | O4: 32250 | P4: 35659 | Q4: 3391 | R4: 34557 | S4: 8062891.9 | T4: 4548429.5 | U4: -3514462.4 | V4: 5096634.5 | W4: 68232273 | X4: 344 | Y4: 1239 | Z4: 696 | AA4: 734402.24 | AB4: 836279.55 | AC4: =AA4-AB4 -> -101877.31 | AD4: =AC4/G4 -> -20375.462 | AE4: 5 | AF4: 0 | AG4: TRUE
A5: 10 | B5: 188 | C5: 15 | D5: 3 | E5: 3 | F5: 15 | G5: 5 | H5: 90.12 | I5: 98.7 | J5: 0.3 | K5: 83744 | L5: 84954 | M5: 27765 | N5: 11246 | O5: 5219 | P5: 42636 | Q5: 4010 | R5: 36044 | S5: 10589209 | T5: 9271102.6 | U5: -1318106.5 | V5: 6858424.8 | W5: 67646764 | X5: 174 | Y5: 1707 | Z5: 201 | AA5: 3157034.7 | AB5: 836279.55 | AC5: =AA5-AB5 -> 2320755.1 | AD5: =AC5/G5 -> 464151.03 | AE5: 5 | AF5: 10 | AG5: TRUE
A6: 10 | B6: 193 | C6: 15 | D6: 3 | E6: 1 | F6: 30 | G6: 5 | H6: 45.06 | I6: 49.35 | J6: 0.3 | K6: 55624 | L6: 93590 | M6: 29025 | N6: 9634 | O6: 27538 | P6: 32831 | Q6: 3271 | R6: 29536 | S6: 10124349 | T6: 5164071 | U6: -4960278.4 | V6: 7813527.1 | W6: 1.9752276e+08 | X6: 586 | Y6: 1819 | Z6: 1946 | AA6: 1262239.1 | AB6: 836279.55 | AC6: =AA6-AB6 -> 425959.6 | AD6: =AC6/G6 -> 85191.92 | AE6: 5 | AF6: 0 | AG6: TRUE
A7: 10 | B7: 188 | C7: 15 | D7: 3 | E7: 1 | F7: 30 | G7: 5 | H7: 90.12 | I7: 98.7 | J7: 0.3 | K7: 75087 | L7: 85301 | M7: 28287 | N7: 9416 | O7: 4646 | P7: 36258 | Q7: 3905 | R7: 27656 | S7: 8181738.9 | T7: 6966386.6 | U7: -1215352.3 | V7: 8982625 | W7: 5.0595782e+08 | X7: 588 | Y7: 1333 | Z7: 2073 | AA7: 401815.26 | AB7: 836279.55 | AC7: =AA7-AB7 -> -434464.29 | AD7: =AC7/G7 -> -86892.859 | AE7: 5 | AF7: 46 | AG7: TRUE
A8: 10 | B8: 192 | C8: 15 | D8: 3 | E8: 1 | F8: 15 | G8: 5 | H8: 45.06 | I8: 49.35 | J8: 0.3 | K8: 65860 | L8: 96265 | M8: 27488 | N8: 11502 | O8: 4753 | P8: 39124 | Q8: 3563 | R8: 37591 | S8: 11197638 | T8: 5223145.9 | U8: -5974492.4 | V8: 8056747.9 | W8: 0 | X8: 144 | Y8: 2022 | Z8: 0 | AA8: 1188262.3 | AB8: 836279.55 | AC8: =AA8-AB8 -> 351982.76 | AD8: =AC8/G8 -> 70396.553 | AE8: 5 | AF8: 1 | AG8: TRUE
A9: 10 | B9: 188 | C9: 15 | D9: 3 | E9: 1 | F9: 15 | G9: 5 | H9: 90.12 | I9: 98.7 | J9: 0.3 | K9: 83862 | L9: 85144 | M9: 27628 | N9: 11355 | O9: 5337 | P9: 43492 | Q9: 4001 | R9: 37104 | S9: 11119606 | T9: 9574713.2 | U9: -1544892.7 | V9: 7875108.6 | W9: 0 | X9: 136 | Y9: 1978 | Z9: 0 | AA9: 3430220.4 | AB9: 836279.55 | AC9: =AA9-AB9 -> 2593940.8 | AD9: =AC9/G9 -> 518788.17 | AE9: 5 | AF9: 13 | AG9: TRUE
A10: 10 | B10: 193 | C10: 15 | D10: 1 | E10: 3 | F10: 30 | G10: 5 | H10: 45.06 | I10: 49.35 | J10: 0.3 | K10: 54206 | L10: 92569 | M10: 27471 | N10: 9304 | O10: 25735 | P10: 30154 | Q10: 3302 | R10: 27773 | S10: 8887766.5 | T10: 4411704.1 | U10: -4476062.4 | V10: 6517385 | W10: 2.2657946e+08 | X10: 617 | Y10: 1300 | Z10: 2274 | AA10: 1057647.9 | AB10: 836279.55 | AC10: =AA10-AB10 -> 221368.32 | AD10: =AC10/G10 -> 44273.663 | AE10: 5 | AF10: 0 | AG10: TRUE
A11: 10 | B11: 188 | C11: 15 | D11: 1 | E11: 3 | F11: 30 | G11: 5 | H11: 90.12 | I11: 98.7 | J11: 0.3 | K11: 73479 | L11: 80058 | M11: 29606 | N11: 9365 | O11: 4579 | P11: 35130 | Q11: 3834 | R11: 27574 | S11: 9596064.7 | T11: 7414965.4 | U11: -2181099.3 | V11: 11009126 | W11: 4.7832283e+08 | X11: 630 | Y11: 1490 | Z11: 2106 | AA11: 1667189.1 | AB11: 836279.55 | AC11: =AA11-AB11 -> 830909.51 | AD11: =AC11/G11 -> 166181.9 | AE11: 5 | AF11: 0 | AG11: TRUE
A12: 10 | B12: 193 | C12: 15 | D12: 1 | E12: 3 | F12: 15 | G12: 5 | H12: 45.06 | I12: 49.35 | J12: 0.3 | K12: 59890 | L12: 94866 | M12: 28047 | N12: 10761 | O12: 31385 | P12: 34663 | Q12: 3385 | R12: 33515 | S12: 8173867.4 | T12: 4512427 | U12: -3661440.4 | V12: 5295664.5 | W12: 1.067828e+08 | X12: 481 | Y12: 1088 | Z12: 862 | AA12: 1142154.3 | AB12: 836279.55 | AC12: =AA12-AB12 -> 305874.73 | AD12: =AC12/G12 -> 61174.945 | AE12: 5 | AF12: 0 | AG12: TRUE
A13: 10 | B13: 188 | C13: 15 | D13: 1 | E13: 3 | F13: 15 | G13: 5 | H13: 90.12 | I13: 98.7 | J13: 0.3 | K13: 82329 | L13: 83864 | M13: 27897 | N13: 10985 | O13: 5221 | P13: 40936 | Q13: 4013 | R13: 34490 | S13: 9143625.7 | T13: 7991009.7 | U13: -1152616 | V13: 6841452.8 | W13: 1.4556912e+08 | X13: 252 | Y13: 1358 | Z13: 488 | AA13: 2937034.9 | AB13: 836279.55 | AC13: =AA13-AB13 -> 2100755.4 | AD13: =AC13/G13 -> 420151.08 | AE13: 5 | AF13: 10 | AG13: TRUE
... A257: 10 | B257: 159 | C257: 10 | D257: 1 | E257: 1 | F257: 15 | G257: 50 | H257: 90.12 | I257: 98.7 | J257: 0.4 | K257: 59578 | L257: 79467 | M257: 31679 | N257: 11163 | O257: 6498 | P257: 47985 | Q257: 4636 | R257: 37332 | S257: 26041105 | T257: 28336542 | U257: 2295437.5 | V257: 9149276.4 | W257: 0 | X257: 2468 | Y257: 1971 | Z257: 0 | AA257: 12225992 | AB257: 5695648 | AC257: =AA257-AB257 -> 6530344 | AD257: =AC257/G257 -> 130606.88 | AE257: 50 | AF257: 678 | AG257: TRUE

Sheet MANOVA 
B2: Experiment Setups
B3: investor_percent_earning_share | C3: 0.3, 0.4
B4: investor_count | C4: 5, 30, 50
B5: investment_rotation_years | C5: 15, 10
B6: nursery_count | C6: 3, 1
B7: police_count | C7: 3, 1
B8: member_count | C8: 30, 15
B9: price_multiplier | C9: 1, 2
B11: Total combinations: | C11: 192
C12: MANOVA Pr(>F)
B13: Independent \Dependent | C13: Native | D13: Exotic | E13: net_running_earning | F13: average.net.investor.profit | G13: independent_laborer | H13: average.m_partners_earning | I13: equally_profitable | J13: member_laborer
B14: nursery count | C14: 0.5651 | D14: 0.7575 | E14: 0.8623 | F14: 0.8837 | G14: 0.5367 | H14: 0.0003169 | I14: 1 | J14: 0.5646
B15: police count | C15: 0.7956 | D15: 0.8999 | E15: 0.6172 | F15: 0.715 | G15: 0.9954 | H15: 0.8946 | I15: 0.4015 | J15: 0.9977
B16: member count | C16: 0.4001 | D16: 0.07386 | E16: 5.107e-05 | F16: 0.00642 | G16: 2.083e-06 | H16: 0.005478 | I16: 0.2077 | J16: 3.816e-15
B17: investor count | C17: 1.458e-09 | D17: < 2.2e-16 | E17: 0.08546 | F17: 1.534e-05 | G17: < 2.2e-16 | H17: 1.768e-05 | I17: 9.888e-12 | J17: < 2.2e-16
B18: price per bdft | C18: 0.9059 | D18: 0.4577 | E18: 6.627e-15 | F18: 6.605e-12 | G18: 0.8918 | H18: 0.06556 | I18: 1.334e-08 | J18: 0.9779
B19: rotation years | C19: < 2.2e-16 | D19: 8.191e-08 | E19: 0.0007399 | F19: 0.009434 | G19: 0.1268 | H19: 0.9458 | I19: 0.4015 | J19: 2.601e-06
B20: investor earning share | C20: 0.9058 | D20: 0.8249 | E20: 0.2729 | F20: 0.0006389 | G20: 0.974 | H20: 0.01595 | I20: 0.6751 | J20: 0.3835
B22: Alpha-level | C22: 0.05 | D22: or | E22: 95% confidence level
B23: This is the p-value associated with the F statistic of a given source. The null hypothesis that the predictor has no effect on the outcome variable is evaluated with regard to this p-value. For a given alpha level, if the p-value is less than alpha, the null hypothesis is rejected. If not, then we fail to reject the null hypothesis. --https://stats.oarc.ucla.edu/sas/output/manova/
H27: Best scenario:
H28: earning share: | I28: 0.3
H29: investor count | I29: 50
H30: rotation year | I30: 15
H31: nursery count | I31: 1
H32: police count | I32: 1
H33: member count | I33: 15
H34: price multiplier | I34: 2
H36: net running earning | I36: 10725375
H37: total investor net earning | I37: 12297393
H38: average investor net earning | I38: 245947.87
H45: Observation
H46: more investors and longer rotation years provide better tree population
H74: Observation
H75: very few investors lead to surge of independent laborers
H76: the fluctuations was just because it's the total number of available laborers
